fibad/__init__.py
fibad/_version.py
fibad/config_utils.py
fibad/download.py
fibad/download_stats.py
fibad/example_benchmarks.py
fibad/fibad.py
fibad/fibad_default_config.toml
fibad/plugin_utils.py
fibad/predict.py
fibad/pytorch_ignite.py
fibad/train.py
fibad/data_sets/__init__.py
fibad/data_sets/data_set_registry.py
fibad/data_sets/example_cifar_data_set.py
fibad/data_sets/hsc_data_set.py
fibad/downloadCutout/LINCC_README.md
fibad/downloadCutout/README.md
fibad/downloadCutout/downloadCutout.py
fibad/models/__init__.py
fibad/models/example_autoencoder.py
fibad/models/example_cnn_classifier.py
fibad/models/model_registry.py
fibad_cli/main.py
fibad-0.1.2.dist-info/LICENSE
fibad-0.1.2.dist-info/METADATA
fibad-0.1.2.dist-info/WHEEL
fibad-0.1.2.dist-info/entry_points.txt
fibad-0.1.2.dist-info/top_level.txt
fibad-0.1.2.dist-info/RECORD
