Metadata-Version: 2.1
Name: fibad
Version: 0.1.2
Author-email: LINCC Frameworks <mtauraso@uw.edu>
License: MIT License
Project-URL: Source Code, https://github.com/lincc-frameworks/fibad
Classifier: Development Status :: 4 - Beta
Classifier: License :: OSI Approved :: MIT License
Classifier: Intended Audience :: Developers
Classifier: Intended Audience :: Science/Research
Classifier: Operating System :: OS Independent
Classifier: Programming Language :: Python
Requires-Python: >=3.9
License-File: LICENSE
Requires-Dist: astropy
Requires-Dist: pytorch-ignite
Requires-Dist: toml
Requires-Dist: torch
Requires-Dist: torchvision
Provides-Extra: dev
Requires-Dist: asv ==0.6.4 ; extra == 'dev'
Requires-Dist: jupyter ; extra == 'dev'
Requires-Dist: matplotlib ; extra == 'dev'
Requires-Dist: pre-commit ; extra == 'dev'
Requires-Dist: pytest ; extra == 'dev'
Requires-Dist: pytest-cov ; extra == 'dev'
Requires-Dist: ruff ; extra == 'dev'
Provides-Extra: examples
